setup.py
httprunner_zt/__about__.py
httprunner_zt/__init__.py
httprunner_zt/api.py
httprunner_zt/built_in.py
httprunner_zt/cli.py
httprunner_zt/client.py
httprunner_zt/compat.py
httprunner_zt/context.py
httprunner_zt/exceptions.py
httprunner_zt/loader.py
httprunner_zt/locustfile.py
httprunner_zt/locusts.py
httprunner_zt/logger.py
httprunner_zt/parser.py
httprunner_zt/report.py
httprunner_zt/response.py
httprunner_zt/runner.py
httprunner_zt/utils.py
httprunner_zt/validator.py
httprunner_zt.egg-info/PKG-INFO
httprunner_zt.egg-info/SOURCES.txt
httprunner_zt.egg-info/dependency_links.txt
httprunner_zt.egg-info/requires.txt
httprunner_zt.egg-info/top_level.txt