Metadata-Version: 2.1
Name: httprunner-zt
Version: 1.5.15.1.1
Summary: httprunner定制化
Home-page: https://github.com/
Author: liyubin
Author-email: 1399393088@qq.com
License: MIT Licence
Keywords: pip,httprunner_zt,featureextraction
Platform: any
